pytest_sanic/__init__.py
pytest_sanic/plugin.py
pytest_sanic/utils.py
pytest_sanic-1.7.1.dist-info/entry_points.txt
pytest_sanic-1.7.1.dist-info/LICENSE
pytest_sanic-1.7.1.dist-info/WHEEL
pytest_sanic-1.7.1.dist-info/METADATA
pytest_sanic-1.7.1.dist-info/RECORD
