Metadata-Version: 2.1
Name: pytest-sanic
Version: 1.7.1
Summary: a pytest plugin for Sanic
Home-page: https://github.com/yunstanford/pytest-sanic
License: MIT
Author: Yun Xu
Author-email: yunxu1992@gmail.com
Requires-Python: >=3.6.1
Classifier: License :: OSI Approved :: MIT License
Classifier: Programming Language :: Python :: 3
Classifier: Programming Language :: Python :: 3.7
Classifier: Programming Language :: Python :: 3.8
Classifier: Topic :: Software Development :: Libraries :: Python Modules
Requires-Dist: async_generator (>=1.10,<2.0)
Requires-Dist: httpx (>=0.15.4)
Requires-Dist: pytest (>=5.2)
Requires-Dist: websockets (>=8.1,<9.0)
Project-URL: Documentation, https://pytest-sanic.readthedocs.io/en/latest/
Project-URL: Repository, https://github.com/yunstanford/pytest-sanic
